discord_http/__init__.py
discord_http/__main__.py
discord_http/asset.py
discord_http/audit.py
discord_http/automod.py
discord_http/backend.py
discord_http/channel.py
discord_http/client.py
discord_http/colour.py
discord_http/commands.py
discord_http/context.py
discord_http/cooldowns.py
discord_http/embeds.py
discord_http/emoji.py
discord_http/entitlements.py
discord_http/enums.py
discord_http/errors.py
discord_http/file.py
discord_http/flags.py
discord_http/guild.py
discord_http/http.py
discord_http/integrations.py
discord_http/invite.py
discord_http/member.py
discord_http/mentions.py
discord_http/message.py
discord_http/multipart.py
discord_http/object.py
discord_http/response.py
discord_http/role.py
discord_http/soundboard.py
discord_http/sticker.py
discord_http/tasks.py
discord_http/user.py
discord_http/utils.py
discord_http/view.py
discord_http/voice.py
discord_http/webhook.py
discord_http/gateway/__init__.py
discord_http/gateway/activity.py
discord_http/gateway/cache.py
discord_http/gateway/client.py
discord_http/gateway/enums.py
discord_http/gateway/flags.py
discord_http/gateway/object.py
discord_http/gateway/parser.py
discord_http/gateway/shard.py
discord_http-3.0.1.dist-info/licenses/LICENSE
discord_http-3.0.1.dist-info/METADATA
discord_http-3.0.1.dist-info/WHEEL
discord_http-3.0.1.dist-info/top_level.txt
discord_http-3.0.1.dist-info/RECORD
