Metadata-Version: 2.4
Name: discord.http
Version: 3.0.1
Summary: Python library that handles interactions from Discord POST requests.
Author-email: AlexFlipnote <root@alexflipnote.dev>
License-Expression: MIT
Project-URL: Homepage, https://discordhttp.alexflipnote.dev
Project-URL: Repository, https://github.com/AlexFlipnote/discord.http
Keywords: discord,http,api,interaction,aiohttp,webhook,slash
Requires-Python: <3.14,>=3.11.0
License-File: LICENSE
Requires-Dist: PyNaCl<2,>=1.5.0
Requires-Dist: aiohttp<4,>=3.12.7
Requires-Dist: orjson<4,>=3.10.18
Provides-Extra: dev
Requires-Dist: pyright>=1.1.401; extra == "dev"
Requires-Dist: ruff>=0.11.13; extra == "dev"
Provides-Extra: docs
Requires-Dist: furo>=2024.8.6; extra == "docs"
Requires-Dist: myst-parser>=4.0.1; extra == "docs"
Requires-Dist: sphinx>=8.2.3; extra == "docs"
Requires-Dist: sphinx-autodoc-typehints>=3.2.0; extra == "docs"
Dynamic: license-file
